{
  "people": [
    {
      "username": "asda",
      "lastname": "sdv",
      "middlename": "cvb",
      "phone": "+37494182873",
      "email": "gjerov123321@gmail.com",
      "password": "zsdvczc",
      "gender": "male",
      "country": "Армения",
      "city": "erevan",
      "dob": "2023-07-11",
      "id": "64c8e557-11f8-4ff6-9f4c-242e329c02f2"
    },
    {
      "username": "Dav",
      "lastname": "mat",
      "middlename": "kar",
      "phone": "+37494182873",
      "email": "gjerov12332sdv1@gmail.com",
      "password": "8520",
      "gender": "male",
      "country": "Армения",
      "city": "erevan",
      "dob": "2023-07-05",
      "id": "c760ae1d-8c99-493f-8c70-a37afd0f4df3"
    },
    {
      "username": "Dav",
      "password": "8520",
      "id": "zszgEP8"
    },
    {
      "username": "dsf",
      "password": "xvcb",
      "id": "bzFXpeB"
    },
    {
      "username": {},
      "lastname": {},
      "middlename": {},
      "phone": {},
      "email": {},
      "password": {},
      "gender": {
        "0": {},
        "1": {},
        "2": {}
      },
      "country": {},
      "city": {},
      "dob": {},
      "id": "1b_PXUJ"
    },
    {
      "username": "",
      "lastname": "",
      "middlename": "",
      "phone": "",
      "email": "",
      "password": "",
      "gender": "",
      "country": "",
      "city": "",
      "dob": "",
      "id": "OCvy2vh"
    },
    {
      "username": "Davo",
      "lastname": "mat",
      "middlename": "kar",
      "phone": "+37494182873",
      "email": "gjerov12332sdv1@gmail.com",
      "password": "8520",
      "gender": "male",
      "country": "Армения",
      "city": "erevan",
      "dob": "2023-06-28",
      "id": "38fdd923-39b5-4e92-991f-0f6458d04607"
    },
    {
      "username": "XZ",
      "password": "xc",
      "id": "rTCxEIV"
    },
    {
      "username": "Dav",
      "password": "8520",
      "id": "OuhXktB"
    },
    {
      "username": "Dav",
      "password": "8520",
      "id": "5xv5ZgG"
    }
  ]
}